lhpapi/__init__.py
lhpapi/api_utils.py
lhpapi/bb_api.py
lhpapi/be_api.py
lhpapi/bw_api.py
lhpapi/by_api.py
lhpapi/hb_api.py
lhpapi/he_api.py
lhpapi/hh_api.py
lhpapi/mv_api.py
lhpapi/ni_api.py
lhpapi/nw_api.py
lhpapi/rp_api.py
lhpapi/sh_api.py
lhpapi/sl_api.py
lhpapi/sn_api.py
lhpapi/st_api.py
lhpapi/th_api.py
lhpapi-1.0.9.dist-info/METADATA
lhpapi-1.0.9.dist-info/WHEEL
lhpapi-1.0.9.dist-info/licenses/LICENSE
lhpapi-1.0.9.dist-info/RECORD
