Metadata-Version: 2.4
Name: lhpapi
Version: 1.0.9
Summary: API to retrieve data from the Länderübergreifendes Hochwasser Portal (LHP)
Project-URL: Homepage, https://github.com/stephan192/lhpapi
Project-URL: Issues, https://github.com/stephan192/lhpapi/issues
Author-email: stephan192 <stephan192@outlook.com>
License-File: LICENSE
Keywords: hochwasser,lhp,lhpapi
Classifier: Development Status :: 5 - Production/Stable
Classifier: License :: OSI Approved :: MIT License
Classifier: Operating System :: OS Independent
Classifier: Programming Language :: Python :: 3
Requires-Python: >=3.11
Requires-Dist: beautifulsoup4>=4.12.2
Requires-Dist: lxml>=4.9.4
Requires-Dist: requests>=2.31.0
Requires-Dist: tzdata>=2024.1
